teamleader/__init__.py
teamleader/client.py
teamleader/helpFunctions.py
teamleader/teamleaderMethods.py
teamleader/teamleaderObjects.py
teamleader/teamleaderStores.py
teamleader-1.1.0.dist-info/LICENSE.txt
teamleader-1.1.0.dist-info/METADATA
teamleader-1.1.0.dist-info/WHEEL
teamleader-1.1.0.dist-info/top_level.txt
teamleader-1.1.0.dist-info/RECORD
