Metadata-Version: 2.1
Name: teamleader
Version: 1.1.0
Summary: A layer on top of the Teamleader v2 API
Home-page: https://github.com/HeroPP/Teamleader
Download-URL: https://github.com/HeroPP/Teamleader/archive/refs/tags/v1.1.0.tar.gz
Author: Jaap
Author-email: jaap1@me.com
License: MIT
Keywords: Teamleader,API,CRM
Platform: UNKNOWN
Classifier: Development Status :: 3 - Alpha
Classifier: Intended Audience :: Developers
Classifier: Topic :: Software Development :: Build Tools
Classifier: License :: OSI Approved :: MIT License
Classifier: Programming Language :: Python :: 3
License-File: LICENSE.txt
Requires-Dist: certifi
Requires-Dist: charset-normalizer
Requires-Dist: idna
Requires-Dist: oauthlib
Requires-Dist: pickle5
Requires-Dist: ratelimit
Requires-Dist: requests
Requires-Dist: requests-oauthlib
Requires-Dist: urllib3
